copychat/__init__.py
copychat/_version.py
copychat/cli.py
copychat/cli_utilities.py
copychat/core.py
copychat/format.py
copychat/mcp_server.py
copychat/patterns.py
copychat/sources.py
copychat-0.7.2.dist-info/METADATA
copychat-0.7.2.dist-info/WHEEL
copychat-0.7.2.dist-info/entry_points.txt
copychat-0.7.2.dist-info/top_level.txt
copychat-0.7.2.dist-info/RECORD
