Metadata-Version: 2.4
Name: copychat
Version: 0.7.2
Summary: Easily copy code for LLM context
License: MIT
Requires-Python: >=3.10
Requires-Dist: typer>=0.9.0
Requires-Dist: rich>=13.7.0
Requires-Dist: pyperclip>=1.8.2
Requires-Dist: pathspec>=0.12.1
Requires-Dist: tiktoken>=0.6.0
Requires-Dist: gitpython>=3.1.42
Requires-Dist: fastmcp>=2.8.1
